<?xml version = '1.0' encoding = 'UTF-8'?>
<Relation class="oracle.dbtools.crest.model.design.logical.Relation" name="FK_TIE_EMP" directorySegmentName="seg_0" id="815A0F27-9029-90C7-1A55-27A52DF39F92">
<createdBy>elder</createdBy>
<createdTime>2023-09-03 02:20:53 UTC</createdTime>
<ownerDesignName>FASE1</ownerDesignName>
<engineerTo>
<item key="7CE9DCB6-BDC6-D070-ED11-3651B111B155" value="true"/>
</engineerTo>
<identifying>false</identifying>
<optionalSource>true</optionalSource>
<optionalTarget>false</optionalTarget>
<sourceCardinality>1</sourceCardinality>
<sourceEntity>8C2C1F6E-2BD0-FCBF-247B-8C062FE5AF9C</sourceEntity>
<targetCardinalityString>*</targetCardinalityString>
<targetEntity>5B080AEE-8649-6E9F-3AE4-BCC21AC758B5</targetEntity>
<transferable>true</transferable>
<deleteRule>NO ACTION</deleteRule>
</Relation>