<?xml version = '1.0' encoding = 'UTF-8'?>
<Relation class="oracle.dbtools.crest.model.design.logical.Relation" name="FK_CAT_PRO" directorySegmentName="seg_0" id="CE0AE01D-8139-7808-D981-CAACD3ECE1FD">
<createdBy>elder</createdBy>
<createdTime>2023-09-03 02:28:15 UTC</createdTime>
<ownerDesignName>FASE1</ownerDesignName>
<engineerTo>
<item key="7CE9DCB6-BDC6-D070-ED11-3651B111B155" value="true"/>
</engineerTo>
<identifying>false</identifying>
<optionalSource>true</optionalSource>
<optionalTarget>false</optionalTarget>
<sourceCardinality>1</sourceCardinality>
<sourceEntity>FE4E0783-5303-5D85-61FF-960378DD125B</sourceEntity>
<targetCardinalityString>*</targetCardinalityString>
<targetEntity>DA42EBBA-A6BC-0C8F-9CCD-F98FCDE536A4</targetEntity>
<transferable>true</transferable>
<deleteRule>NO ACTION</deleteRule>
</Relation>